{"Modules":[{"Key":"sample","Source":"./modules/sample","Dir":"modules/sample"},{"Key":"virtual_machine","Source":"./modules/virtual_machine","Dir":"modules/virtual_machine"},{"Key":"kubernetes.vsphere_data","Source":"../vsphere_data","Dir":"modules/vsphere_data"},{"Key":"elastic-stack","Source":"./modules/elastic-stack","Dir":"modules/elastic-stack"},{"Key":"","Source":"","Dir":"."},{"Key":"lab","Source":"./modules/lab","Dir":"modules/lab"},{"Key":"repo","Source":"./modules/repo","Dir":"modules/repo"},{"Key":"kubernetes","Source":"./modules/kubernetes","Dir":"modules/kubernetes"},{"Key":"vsphere_provider","Source":"./modules/vsphere_provider","Dir":"modules/vsphere_provider"},{"Key":"vsphere_data","Source":"./modules/vsphere_data","Dir":"modules/vsphere_data"}]}